{"cameraMode":{"drawMode":0,"name":"Shaded","section":"Shading Mode"},"sceneLighting":true,"audioPlay":false,"sceneViewState":{"m_AlwaysRefresh":false,"showFog":true,"showSkybox":true,"showFlares":true,"showImageEffects":true,"showParticleSystems":true,"showVisualEffectGraphs":true,"m_FxEnabled":true},"in2DMode":false,"pivot":{"x":-3.0557873249053957,"y":10.013150215148926,"z":-5.0755085945129398},"rotation":{"x":0.4803008437156677,"y":-0.0013155352789908648,"z":0.0007216865778900683,"w":0.8770997524261475},"size":3.1874313354492189,"orthographic":false}